templatizer/__init__.py
templatizer/py.typed
templatizer/run.py
templatizer/templatable.py
templatizer/yamlblob.py
templatizer/k8s/__init__.py
templatizer/k8s/base.py
templatizer/k8s/gen.py
pytemplatize-0.0.10.dist-info/LICENSE
pytemplatize-0.0.10.dist-info/METADATA
pytemplatize-0.0.10.dist-info/WHEEL
pytemplatize-0.0.10.dist-info/top_level.txt
pytemplatize-0.0.10.dist-info/RECORD
