Metadata-Version: 2.1
Name: pytemplatize
Version: 0.0.10
Summary: Sprinkling imperative logic into your template generation process.
Home-page: https://github.com/miselin/templatizer
Author: Matt Iselin
Author-email: matthew@theiselins.net
Project-URL: Bug Tracker, https://github.com/miselin/templatizer/issues
Classifier: Programming Language :: Python :: 3
Classifier: License :: OSI Approved :: MIT License
Classifier: Operating System :: OS Independent
Requires-Python: >=3.6
License-File: LICENSE
